spatialkit/__init__.py
spatialkit/camera/__init__.py
spatialkit/camera/base.py
spatialkit/camera/doublesphere.py
spatialkit/camera/equirectangular.py
spatialkit/camera/fisheye.py
spatialkit/camera/omnidirectional.py
spatialkit/camera/perspective.py
spatialkit/camera/radial_base.py
spatialkit/common/__init__.py
spatialkit/common/constant.py
spatialkit/common/exceptions.py
spatialkit/common/logger.py
spatialkit/geom/__init__.py
spatialkit/geom/epipolar.py
spatialkit/geom/multiview.py
spatialkit/geom/pointcloud.py
spatialkit/geom/pose.py
spatialkit/geom/registration.py
spatialkit/geom/rotation.py
spatialkit/geom/tf.py
spatialkit/imgproc/__init__.py
spatialkit/imgproc/img_tf.py
spatialkit/imgproc/synthesis.py
spatialkit/io/__init__.py
spatialkit/io/config.py
spatialkit/io/image.py
spatialkit/io/video.py
spatialkit/markers/__init__.py
spatialkit/markers/apriltag_detector.py
spatialkit/markers/base.py
spatialkit/markers/marker.py
spatialkit/markers/opencv_detector.py
spatialkit/markers/stag_detector.py
spatialkit/ops/__init__.py
spatialkit/ops/umath.py
spatialkit/ops/uops.py
spatialkit/vis2d/__init__.py
spatialkit/vis2d/convert.py
spatialkit/vis2d/display.py
spatialkit/vis2d/draw.py
spatialkit/vis3d/__init__.py
spatialkit/vis3d/api.py
spatialkit/vis3d/boxes.py
spatialkit/vis3d/circles.py
spatialkit/vis3d/common.py
spatialkit/vis3d/indicators.py
spatialkit/vis3d/lines.py
spatialkit/vis3d/o3dutils.py
spatialkit/vis3d/planes.py
spatialkit/vis3d/textures.py
spatialkit-0.3.3.dist-info/licenses/LICENSE
spatialkit-0.3.3.dist-info/METADATA
spatialkit-0.3.3.dist-info/WHEEL
spatialkit-0.3.3.dist-info/top_level.txt
spatialkit-0.3.3.dist-info/RECORD
