Metadata-Version: 2.4
Name: spatialkit
Version: 0.3.3
Summary: A spatial computing toolkit for 3D vision and robotics
Author-email: Sehyun Cha <cshyundev@gmail.com>
License: MIT
Project-URL: Homepage, https://github.com/cshyundev/spatialkit
Project-URL: Repository, https://github.com/cshyundev/spatialkit
Project-URL: Issues, https://github.com/cshyundev/spatialkit/issues
Keywords: spatial-computing,3d-vision,geometry,robotics,pytorch,computer-vision
Classifier: Development Status :: 3 - Alpha
Classifier: Intended Audience :: Developers
Classifier: Intended Audience :: Science/Research
Classifier: License :: OSI Approved :: MIT License
Classifier: Programming Language :: Python :: 3
Classifier: Programming Language :: Python :: 3.10
Classifier: Programming Language :: Python :: 3.11
Classifier: Programming Language :: Python :: 3.12
Classifier: Topic :: Scientific/Engineering :: Artificial Intelligence
Classifier: Topic :: Scientific/Engineering :: Image Processing
Requires-Python: >=3.10
License-File: LICENSE
Requires-Dist: numpy>=1.26.0
Requires-Dist: opencv-python>=4.5.0
Requires-Dist: torch>=2.0.0
Requires-Dist: scipy>=1.11.0
Requires-Dist: matplotlib>=3.7.0
Requires-Dist: scikit-image>=0.21.0
Requires-Dist: tifffile>=2023.7.0
Requires-Dist: Pillow>=10.0.0
Requires-Dist: PyYAML>=6.0
Requires-Dist: absl-py>=2.0.0
Requires-Dist: rich>=13.0.0
Requires-Dist: dt-apriltags>=3.1.7
Requires-Dist: stag-python>=1.1.1
Requires-Dist: open3d>=0.19.0
Provides-Extra: dev
Requires-Dist: pytest>=8.4.1; extra == "dev"
Requires-Dist: pytest-cov; extra == "dev"
Dynamic: license-file
